EcodeX/__init__.py
EcodeX-0.0.0.3.dist-info/METADATA
EcodeX-0.0.0.3.dist-info/WHEEL
EcodeX-0.0.0.3.dist-info/top_level.txt
EcodeX-0.0.0.3.dist-info/RECORD
