Metadata-Version: 2.1
Name: EcodeX
Version: 0.0.0.3
Summary: SpadaOS官方GUI库EcodeX
Home-page: UNKNOWN
Author: 欣源科技EcoSpace
Author-email: ecospace@qq.com
License: UNKNOWN
Platform: UNKNOWN
Classifier: Development Status :: 4 - Beta
Classifier: Intended Audience :: Developers
Classifier: Programming Language :: Python
Classifier: Programming Language :: Python :: 3
